[
  {
    "id": "9f5e41d0-f5e3-46b3-a04e-9d96ff39d490",
    "title": "U5 - Verspätungen nach einer bereits behobenen Störung"
  },
  {
    "id": "3a1856a7-296d-4bf9-b5d8-d12ecc5db496",
    "title": "Bus 164 - Verspätungen und einzelne Ausfälle wegen eines Verkehrsunfalls"
  },
  {
    "id": "5e14100f-1bc6-4df4-a5a6-e2c9c3181841",
    "title": "Tram 16,27 - Verspätungen und einzelne Ausfälle wegen einer Betriebsstörung"
  },
  {
    "id": "79e53696-7c80-46d7-b394-b15a15cbd2d5",
    "title": "Bus SEV 18 - Verspätungen, Ausfälle und vorzeitige Wendungen wegen starken Verkehrsaufkommens"
  },
  {
    "id": "2f6bea33-b4df-4df1-b9b8-60b43d3cdbb9",
    "title": "Bus X35,X36,50 - Verspätungen und einzelne Ausfälle wegen starken Verkehrsaufkommens"
  },
  {
    "id": "7bcd323f-a7c0-40f8-aa93-d1e7651899f2",
    "title": "Bus 51,151,168 - Verspätungen, Ausfälle und vorzeitige Wendungen wegen Bauarbeiten"
  }
]
