[
  {
    "id": "6ce37618-15d9-4bc7-8285-19f4e1c34d50",
    "title": "U3 - Zeitweise Unregelmäßigkeiten wegen Fahrzeugausfällen"
  },
  {
    "id": "06efdb39-ac7a-4e48-a763-77739f9a4740",
    "title": "U2,U8 - Unterbrechung von Freitag ca. 22:30 Uhr bis Sonntag Betriebsschluss zwischen Hauptbahnhof und Hohenzollernplatz, U8 fährt nur Hauptbahnhof <> Neuperlach Zentrum"
  },
  {
    "id": "998ae167-7c57-4ddb-b0b4-c4be14283b0d",
    "title": "U1,U2 - Verspätungen, Ausfälle und vorzeitige Wendungen wegen einer Betriebsstörung"
  },
  {
    "id": "1a6354c5-e340-45fa-b155-b6439100162d",
    "title": "Bus, Tram - Verspätungen wegen bevorstehender Sicherheitskonferenz"
  }
]
